canonicalwebteam/store_base/__init__.py
canonicalwebteam/store_base/app.py
canonicalwebteam/store_base/data/licenses.json
canonicalwebteam/store_base/handlers.py
canonicalwebteam/store_base/macaroon_debug.py
canonicalwebteam/store_base/packages/__init__.py
canonicalwebteam/store_base/packages/logic.py
canonicalwebteam/store_base/packages/views.py
canonicalwebteam/store_base/sample_blueprint/views.py
canonicalwebteam/store_base/utils/__init__.py
canonicalwebteam/store_base/utils/config.py
canonicalwebteam/store_base/utils/constants.py
canonicalwebteam/store_base/utils/extensions.py
canonicalwebteam/store_base/utils/helpers.py
canonicalwebteam/templates/storebase.html
canonicalwebteam_store_base-1.3.0.dist-info/LICENSE
canonicalwebteam_store_base-1.3.0.dist-info/METADATA
canonicalwebteam_store_base-1.3.0.dist-info/WHEEL
canonicalwebteam_store_base-1.3.0.dist-info/RECORD
