Metadata-Version: 2.1
Name: canonicalwebteam-store-base
Version: 1.3.0
Summary: An application base for all stores
License: GPL3
Author: Canonical Webteam
Author-email: webteam@canonical.com
Requires-Python: >=3.8.1,<4.0
Classifier: License :: Other/Proprietary License
Classifier: Programming Language :: Python :: 3
Classifier: Programming Language :: Python :: 3.9
Classifier: Programming Language :: Python :: 3.10
Classifier: Programming Language :: Python :: 3.11
Classifier: Programming Language :: Python :: 3.12
Requires-Dist: Flask-WTF (>=1.0.1,<2.0.0)
Requires-Dist: canonicalwebteam.flask-base (>=1.1.0,<3.0.0)
Requires-Dist: canonicalwebteam.store-api (>=5.0.0,<6.0.0)
Requires-Dist: flake8 (>=6.0.0,<7.0.0)
Requires-Dist: pipenv (>=2022.12.19,<2023.0.0)
Requires-Dist: python-dotenv (>=0.20.0,<0.21.0)
Requires-Dist: responses (>=0.22.0,<0.23.0)
Requires-Dist: talisker (>=0.21.3,<0.22.0)
